pulseeco/_version.py
pulse_eco_ha-1.0.0.dist-info/METADATA
pulse_eco_ha-1.0.0.dist-info/WHEEL
pulse_eco_ha-1.0.0.dist-info/licenses/LICENSE
pulse_eco_ha-1.0.0.dist-info/RECORD
