Metadata-Version: 2.1
Name: pulse-eco-ha
Version: 1.0.0
Summary: pulse.eco API wrapper
Project-URL: Bug Tracker, https://github.com/mxilievski/pulse-eco-ha/issues
Project-URL: Homepage, https://github.com/mxilievski/pulse-eco-ha
Author-email: martinkozle <martinkozle@yahoo.com>, mxilievski <mxilievski@gmail.com>
License-Expression: MIT
License-File: LICENSE
Keywords: air,air pollution,air quality index,api,aqi,eco,pollution,pulse,pulse.eco,python,quality,wrapper
Classifier: Development Status :: 5 - Production/Stable
Classifier: License :: OSI Approved :: MIT License
Classifier: Natural Language :: English
Classifier: Operating System :: OS Independent
Classifier: Programming Language :: Python
Classifier: Programming Language :: Python :: 3
Classifier: Topic :: Scientific/Engineering :: Atmospheric Science
Classifier: Topic :: Scientific/Engineering :: Information Analysis
Classifier: Topic :: Software Development
Classifier: Topic :: Software Development :: Libraries
Classifier: Topic :: Software Development :: Libraries :: Python Modules
Classifier: Typing :: Typed
Requires-Python: >=3.8
Requires-Dist: requests>=2.31.0
Provides-Extra: dev
Requires-Dist: ipython; extra == 'dev'
Requires-Dist: pip-tools>=7.3.0; extra == 'dev'
Requires-Dist: pre-commit>=3.5.0; extra == 'dev'
Requires-Dist: pulse-eco-ha[docs,lint,test]; extra == 'dev'
Provides-Extra: docs
Requires-Dist: mkdocs; extra == 'docs'
Requires-Dist: mkdocs-material; extra == 'docs'
Requires-Dist: mkdocstrings[python]; extra == 'docs'
Requires-Dist: pymdown-extensions; extra == 'docs'
Provides-Extra: lint
Requires-Dist: mypy>=1.6.1; extra == 'lint'
Requires-Dist: pulse-eco-ha[types]; extra == 'lint'
Requires-Dist: ruff>=0.1.2; extra == 'lint'
Provides-Extra: test
Requires-Dist: coverage[toml]>=7.3; extra == 'test'
Requires-Dist: pytest; extra == 'test'
Requires-Dist: python-dotenv; extra == 'test'
Provides-Extra: types
Requires-Dist: types-requests; extra == 'types'
